ofxstatement_be_argenta-1.0.5-py3.7-nspkg.pth
ofxstatement/plugins/argenta.py
ofxstatement_be_argenta/__init__.py
ofxstatement_be_argenta/convert.py
ofxstatement_be_argenta-1.0.5.dist-info/LICENSE
ofxstatement_be_argenta-1.0.5.dist-info/METADATA
ofxstatement_be_argenta-1.0.5.dist-info/WHEEL
ofxstatement_be_argenta-1.0.5.dist-info/entry_points.txt
ofxstatement_be_argenta-1.0.5.dist-info/namespace_packages.txt
ofxstatement_be_argenta-1.0.5.dist-info/top_level.txt
ofxstatement_be_argenta-1.0.5.dist-info/zip-safe
ofxstatement_be_argenta-1.0.5.dist-info/RECORD
