Metadata-Version: 2.1
Name: ofxstatement-be-argenta
Version: 1.0.5
Summary: ofxstatement plugin for Argenta
Home-page: https://github.com/woutbr/ofxstatement-be-argenta
Author: Wout Breugelmans
Author-email: Wout.Breugelmans+ofxstatement@gmail.com
License: MIT
Keywords: ofx,ofxstatement,argenta
Platform: UNKNOWN
Classifier: Development Status :: 5 - Production/Stable
Classifier: Programming Language :: Python :: 3
Classifier: Natural Language :: English
Classifier: Topic :: Office/Business :: Financial :: Accounting
Classifier: Topic :: Utilities
Classifier: Environment :: Console
Classifier: Operating System :: OS Independent
Classifier: License :: OSI Approved :: MIT License
Requires-Dist: ofxstatement (>=0.6.1)
Requires-Dist: openpyxl (>=2.6.2)
Requires-Dist: click (>=6.7)
